<?xml version="1.0" encoding="utf-8"?>
<!-- Automatically translated with the help of google translate.-->
<!-- Sun Aug  4 14:59:14 2024-->
<GameData>
	<LocalizedText>
		<Replace Tag="LOC_LEADER_YUZU_NAME" Language="fr_FR">
			<Text>Pamplemousse</Text>
		</Replace>
		<Replace Tag="LOC_TRAIT_LEADER_VITALITY_NAME" Language="fr_FR">
			<Text>vitalité</Text>
		</Replace>
		<Replace Tag="LOC_TRAIT_LEADER_VITALITY_DESCRIPTION" Language="fr_FR">
			<Text>Une unité peut récupérer entièrement [ICON_Damaged] points de vie en 1 [ICON_Turn] tour dans votre cellule de territoire.</Text>
		</Replace>
		<Replace Tag="LOC_CIVILIZATION_POMELO_HOUSE_NAME" Language="fr_FR">
			<Text>Yuzuya</Text>
		</Replace>
		<Replace Tag="LOC_CIVILIZATION_POMELO_HOUSE_ADJECTIVE" Language="fr_FR">
			<Text>Yuzuya</Text>
		</Replace>
		<Replace Tag="LOC_CIVILIZATION_POMELO_HOUSE_DESCRIPTION" Language="fr_FR">
			<Text>Yuzuya</Text>
		</Replace>
		<Replace Tag="LOC_TRAIT_FOX_CLAN_ORACLE_DESCRIPTION" Language="fr_FR">
			<Text>Le sanctuaire Inari gagne +1 [ICON_Faith] Foi pour chaque plantation, ranch ou camp adjacent. Les plantations, ranchs ou camps adjacents au sanctuaire Inari gagnent +1 [ICON_Faith] de foi et offrent +1 d'agrément [ICON_Amenities].</Text>
		</Replace>
		<Replace Tag="LOC_TRAIT_FOX_CLAN_ORACLE_NAME" Language="fr_FR">
			<Text>Oracle du Renard</Text>
		</Replace>
		<Replace Tag="LOC_PEDIA_LEADERS_PAGE_LEADER_YUZU_QUOTE" Language="fr_FR">
			<Text>Ah baa baa baa. . .</Text>
		</Replace>
		<Replace Tag="LOC_LOADING_INFO_LEADER_YUZU" Language="fr_FR">
			<Text>Fille renarde vive et mignonne, elle était autrefois un esprit renard dans le sanctuaire à côté de chez elle. Cependant, pour certaines raisons, elle a conservé les caractéristiques des oreilles et de la queue mais a définitivement perdu son pouvoir magique. elle sera paresseuse à la maison. Pour son propre développement, Insatisfaction corporelle insatisfaisante.</Text>
		</Replace>
		<Replace Tag="LOC_CITY_NAME_FOXOO" Language="fr_FR">
			<Text>maison de renard</Text>
		</Replace>
		<Replace Tag="LOC_DISTRICT_INARI_SHRINE_NAME" Language="fr_FR">
			<Text>Sanctuaire Inari</Text>
		</Replace>
		<Replace Tag="LOC_DISTRICT_INARI_SHRINE_DESCRIPTION" Language="fr_FR">
			<Text>Une zone spéciale. Une fois terminé, le coût de foi [ICON_Faith] requis pour le parrainage d'un grand homme est de -8 % (calcul de multiplication) ; cela ajoute 1 foi [ICON_Faith] à la ville d'où part la route commerciale [ICON_TradeRoute].</Text>
		</Replace>
		<Replace Tag="LOC_Inari_Camp_Faith" Language="fr_FR">
			<Text>+{1_num} [ICON_Faith] Foi des camps adjacents.</Text>
		</Replace>
		<Replace Tag="LOC_Inari_Plantation_Faith" Language="fr_FR">
			<Text>+{1_num} [ICON_Faith] Foi des plantations adjacentes.</Text>
		</Replace>
		<Replace Tag="LOC_Inari_Pasture_Faith" Language="fr_FR">
			<Text>+{1_num} [ICON_Faith] Foi des pâturages adjacents.</Text>
		</Replace>
		<Replace Tag="LOC_IMPROVEMENT_FOX_HOUSE_NAME" Language="fr_FR">
			<Text>cabane de renard</Text>
		</Replace>
		<Replace Tag="LOC_IMPROVEMENT_FOX_HOUSE_DESCRIPTION" Language="fr_FR">
			<Text>Une amélioration unique qui ne peut pas être construite sur la neige. Elle peut être construite sur des plaines, des déserts, des prairies et des forêts. Elle ne peut pas être construite à côté d'une autre cabane de renard. +1[ICON_Culture]Culture +1[ICON_Housing]Logement, +1 Charisme pour les cellules adjacentes. Produit la foi [ICON_Faith] en fonction de la valeur du charme. [NEWLINE] Chaque sanctuaire Inari adjacent +1 culture [ICON_Culture] ; chaque plantation adjacente +1 or [ICON_Gold] ; chaque pâturage adjacent +1 nourriture [ICON_Food] ; chaque camp adjacent +1 [ ICON_Production] productivité. Après avoir déverrouillé &quot;Flight&quot;, il fournira des performances touristiques [ICON_Tourism] équivalentes à la sortie de [ICON_Faith] Faith.</Text>
		</Replace>
		<Replace Tag="LOC_LEADER_MOONCU_NAME" Language="fr_FR">
			<Text>confinement</Text>
		</Replace>
		<Replace Tag="LOC_TRAIT_LEADER_REFRESHING_NAME" Language="fr_FR">
			<Text>rafraîchissant</Text>
		</Replace>
		<Replace Tag="LOC_TRAIT_LEADER_REFRESHING_DESCRIPTION" Language="fr_FR">
			<Text>Lorsque la religion que vous créez devient votre religion principale, vous gagnez aléatoirement une [ICON_CivicBoosted] Inspiration et une [ICON_TechBoosted] Eureka. Les Terres Saintes reçoivent en outre d’importants bonus de contiguïté provenant d’autres régions. +12 % de productivité [ICON_Production] pour les zones de construction, les merveilles et les projets.</Text>
		</Replace>
		<Replace Tag="LOC_CIVILIZATION_SEA_OF_MOONLIGHT_NAME" Language="fr_FR">
			<Text>mer au clair de lune</Text>
		</Replace>
		<Replace Tag="LOC_CIVILIZATION_SEA_OF_MOONLIGHT_ADJECTIVE" Language="fr_FR">
			<Text>mer au clair de lune</Text>
		</Replace>
		<Replace Tag="LOC_CIVILIZATION_SEA_OF_MOONLIGHT_DESCRIPTION" Language="fr_FR">
			<Text>mer au clair de lune</Text>
		</Replace>
		<Replace Tag="LOC_TRAIT_MEOW_AT_DAWN_DESCRIPTION" Language="fr_FR">
			<Text>Construisez une ville et obtenez 1 unité de reconnaissance [ICON_Unit]. Si vous activez &quot;Cat Scout&quot;, vous obtiendrez un éclaireur [ICON_Unit] supplémentaire, une unité d'éclaireur [ICON_Unit] +1 [ICON_Movement] en puissance de mouvement et +7 [ICON_Strength] en puissance de combat pendant le combat.</Text>
		</Replace>
		<Replace Tag="LOC_TRAIT_MEOW_AT_DAWN_NAME" Language="fr_FR">
			<Text>Miaou à l'aube</Text>
		</Replace>
		<Replace Tag="LOC_LOADING_INFO_LEADER_MOONCU" Language="fr_FR">
			<Text>C'est une fille aux oreilles de chat avec une tête de cheveux blancs comme neige et brillants. J'aime porter toutes sortes de vêtements et j'aime aussi le cosplay. Sa personnalité est un peu terne et les changements d'humeur se reflètent dans ses oreilles et sa queue. Si vous aimez manger, la graisse s’accumulera dans votre poitrine.</Text>
		</Replace>
		<Replace Tag="LOC_CITY_NAME_CATOO" Language="fr_FR">
			<Text>Commande Miaou Miaou</Text>
		</Replace>
		<Replace Tag="LOC_ABILITY_MEOW_AT_DAWN_NAME" Language="fr_FR">
			<Text>Miaou à l'aube</Text>
		</Replace>
		<Replace Tag="LOC_ABILITY_MEOW_AT_DAWN_DESCRIPTION" Language="fr_FR">
			<Text>Miao Ming Chuxiao : unité de reconnaissance [ICON_Unit] +1 [ICON_Movement] puissance de mouvement, +7 [ICON_Strength] puissance de combat pendant le combat.</Text>
		</Replace>
		<Replace Tag="LOC_ABILITY_MEOW_AT_DAWN" Language="fr_FR">
			<Text>Miaomingchuxiao+7[ICON_Strength]</Text>
		</Replace>
		<Replace Tag="LOC_Meow_Science" Language="fr_FR">
			<Text>+{1_num} [ICON_Science] La valeur de foi provient des zones adjacentes.</Text>
		</Replace>
		<Replace Tag="LOC_Meow_Wonder_Science" Language="fr_FR">
			<Text>+{1_num} [ICON_Science] Foi des merveilles adjacentes.</Text>
		</Replace>
		<Replace Tag="LOC_DISTRICT_MEOW_ACADEMY_NAME" Language="fr_FR">
			<Text>Académie Miaou</Text>
		</Replace>
		<Replace Tag="LOC_MODIFIER_REFRESHING_HOLY" Language="fr_FR">
			<Text>+{1_num} [ICON_Faith] La valeur de foi vient de Qinxin.</Text>
		</Replace>
		<Replace Tag="LOC_DISTRICT_MEOW_ACADEMY_DESCRIPTION" Language="fr_FR">
			<Text>Une zone spécialisée qui n'obtient que d'énormes bonus adjacents des zones et des merveilles. Le bonus adjacent [ICON_Science]Tech fournit également une valeur [ICON_Culture]Culture.</Text>
		</Replace>
		<Replace Tag="LOC_CITY_NAME_CATAWINKLE" Language="fr_FR">
			<Text>Camp Miaou Miaou</Text>
		</Replace>
		<Replace Tag="LOC_CITY_NAME_CATSPUR" Language="fr_FR">
			<Text>Deuxième camp Miao Miao</Text>
		</Replace>
		<Replace Tag="LOC_CITY_NAME_CATTIVIA" Language="fr_FR">
			<Text>Camp de la frontière occidentale</Text>
		</Replace>
		<Replace Tag="LOC_CITY_NAME_CATSANDCASTLES" Language="fr_FR">
			<Text>falaise de glace</Text>
		</Replace>
		<Replace Tag="LOC_CITY_NAME_CATTYHAVEN" Language="fr_FR">
			<Text>Troisième camp Meow Meow</Text>
		</Replace>
		<Replace Tag="LOC_CITY_NAME_CATTIVILLE" Language="fr_FR">
			<Text>Miaou Miaou Zhongzhou</Text>
		</Replace>
		<Replace Tag="LOC_CITY_NAME_CATTYSHIRE" Language="fr_FR">
			<Text>Ville de transport de Miaomiao</Text>
		</Replace>
		<Replace Tag="LOC_CITY_NAME_CATTYSPIRE" Language="fr_FR">
			<Text>Marché nocturne de Meow Meow</Text>
		</Replace>
		<Replace Tag="LOC_CITY_NAME_CATTYGLOW" Language="fr_FR">
			<Text>Miaou Miaou Nancheng</Text>
		</Replace>
		<Replace Tag="LOC_CITY_NAME_CATTYBRIGHT" Language="fr_FR">
			<Text>Miaou Meow Ville du Nord</Text>
		</Replace>
		<Replace Tag="LOC_CITY_NAME_FOXFIRE" Language="fr_FR">
			<Text>Ville légère de Fox</Text>
		</Replace>
		<Replace Tag="LOC_CITY_NAME_FOXTROT" Language="fr_FR">
			<Text>Village des esprits du renard</Text>
		</Replace>
		<Replace Tag="LOC_CITY_NAME_FOXHOLLOW" Language="fr_FR">
			<Text>Forêt de danse du renard</Text>
		</Replace>
		<Replace Tag="LOC_CITY_NAME_FOXGROVE" Language="fr_FR">
			<Text>Ville de montagne de Huawei</Text>
		</Replace>
		<Replace Tag="LOC_CITY_NAME_FOXDEN" Language="fr_FR">
			<Text>Forêt de Foxfire</Text>
		</Replace>
		<Replace Tag="LOC_CITY_NAME_FOXHILL" Language="fr_FR">
			<Text>Pic de Lune Renard</Text>
		</Replace>
		<Replace Tag="LOC_CITY_NAME_FOXHAM" Language="fr_FR">
			<Text>Vallée de l'Ombre du Renard</Text>
		</Replace>
		<Replace Tag="LOC_CITY_NAME_FOXSPIRE" Language="fr_FR">
			<Text>Vallée du Renard Ming</Text>
		</Replace>
		<Replace Tag="LOC_CITY_NAME_FOXGLOW" Language="fr_FR">
			<Text>Ville culturelle du Renard</Text>
		</Replace>
		<Replace Tag="LOC_CITY_NAME_FOXSHIRE" Language="fr_FR">
			<Text>Jardin du Renard de Jade</Text>
		</Replace>
	</LocalizedText>
</GameData>
