<?xml version="1.0" encoding="utf-8"?>
<!-- Automatically translated with the help of google translate.-->
<!-- Fri May 17 20:27:27 2024-->
<GameData>
	<LocalizedText>
		<Replace Tag="LOC_LEADER_BA_SHIMOE_KOHARU_QUOTE" Language="it_IT">
			<Text>Tutti gli oggetti impuri devono essere inceneriti, inceneriti!</Text>
		</Replace>
		<Replace Tag="LOC_AGENDA_BA_SHIMOE_KOHARU_NAME" Language="it_IT">
			<Text>Nessuna roba volgare!</Text>
		</Replace>
		<Replace Tag="LOC_AGENDA_BA_SHIMOE_KOHARU_DESCRIPTION" Language="it_IT">
			<Text>Mi piacciono le civiltà che non rappresentano alcuna minaccia. Non ama le civiltà con un forte potere militare o le civiltà con città vicine.</Text>
		</Replace>
		<Replace Tag="LOC_DIPLO_KUDO_LEADER_BA_SHIMOE_KOHARU_REASON_ANY" Language="it_IT">
			<Text>(Non sei una minaccia.)</Text>
		</Replace>
		<Replace Tag="LOC_DIPLO_MODIFIER_BA_SHIMOE_KOHARU_HAPPY" Language="it_IT">
			<Text>Nessuna minaccia</Text>
		</Replace>
		<Replace Tag="LOC_DIPLO_WARNING_LEADER_BA_SHIMOE_KOHARU_REASON_ANY" Language="it_IT">
			<Text>(Mi sento minacciato da te.)</Text>
		</Replace>
		<Replace Tag="LOC_DIPLO_MODIFIER_BA_SHIMOE_KOHARU_UNHAPPY" Language="it_IT">
			<Text>sentirsi minacciato</Text>
		</Replace>
		<Replace Tag="LOC_LEADER_BA_SHIMOE_KOHARU_NAME" Language="it_IT">
			<Text>Koharu Shimoe</Text>
		</Replace>
		<Replace Tag="LOC_ECCHI_DAME_NAME" Language="it_IT">
			<Text>Come utilizzare gli oggetti confiscati</Text>
		</Replace>
		<Replace Tag="LOC_ECCHI_DAME_DESCRIPTION" Language="it_IT">
			<Text>La città del giocatore aumenta il cibo [ICON_Food] del 5% per ogni edificio nel quartiere dei teatri.</Text>
		</Replace>
	</LocalizedText>
</GameData>
