<?xml version="1.0" encoding="utf-8"?>
<!-- Automatically translated with the help of google translate.-->
<!-- Sun Dec 29 18:16:40 2024-->
<GameData>
	<LocalizedText>
		<Replace Tag="LOC_CIVILIZATION_OP_LATERANO_NAME" Language="ko_KR">
			<Text>러틀랜드</Text>
		</Replace>
		<Replace Tag="LOC_CIVILIZATION_OP_LATERANO_DESCRIPTION" Language="ko_KR">
			<Text>라테란 교황령</Text>
		</Replace>
		<Replace Tag="LOC_CIVILIZATION_OP_LATERANO_ADJECTIVE" Language="ko_KR">
			<Text>라테란</Text>
		</Replace>
		<Replace Tag="LOC_LEADER_OP_VIRTUOSA_LTRN_NAME" Language="ko_KR">
			<Text>아르투로 지알로</Text>
		</Replace>
		<Replace Tag="LOC_LOADING_INFO_LEADER_OP_VIRTUOSA_LTRN" Language="ko_KR">
			<Text>제가 당신의 개인 음악가가 되어 드리겠습니다. 내가 ... 당신의 마음을 만져 보겠습니다. 당신의 관념은 얼마나 기발하고 당신의 의지는 얼마나 두렵습니까? 당신의 음악이 최고조에 달했을 때 나는 자연스럽게 당신에게 완전히 매료될 것이고, 당신을 위해 나 자신을 연주할 것입니다.</Text>
		</Replace>
		<Replace Tag="LOC_LEADER_OP_VIRTUOSA_LTRN_QUOTE" Language="ko_KR">
			<Text>당신이 보는 것을 보고, 내가 보는 것을 보십시오.</Text>
		</Replace>
		<Replace Tag="LOC_LEADER_OP_ARCHETTO_NAME" Language="ko_KR">
			<Text>시더자·쿵셴</Text>
		</Replace>
		<Replace Tag="LOC_LOADING_INFO_LEADER_OP_ARCHETTO" Language="ko_KR">
			<Text>아버지로부터 궁술을 배우든, 수도원에서 전투 기술을 배우든, Kong Xian은 항상 자신의 기준을 더 높게 유지하는 데 익숙합니다. 더 많은 먹이를 잡기 위해서, 그리고 수도원의 명예를 더 잘 지키기 위해서. 절을 나와 더 넓은 땅을 본 공현은 자신의 화살이 담고 있는 의미를 더욱 분명하게 깨달았다.</Text>
		</Replace>
		<Replace Tag="LOC_LEADER_OP_ARCHETTO_QUOTE" Language="ko_KR">
			<Text>시안에게는 세 가지 선택이 있고 적에게는 세 가지 고통이 있습니다.</Text>
		</Replace>
		<Replace Tag="LOC_LEADER_OP_FIAMMETTA_NAME" Language="ko_KR">
			<Text>피아메타</Text>
		</Replace>
		<Replace Tag="LOC_LOADING_INFO_LEADER_OP_FIAMMETTA" Language="ko_KR">
			<Text>라테라노 공증인 사무실의 선임 국장 피아메타(Fiametta)입니다. 일반적으로 Mastima와 함께 행동하며 자신이 Mastima의 감독자라고 주장하며 Mastima가 외부 접촉을 통해 라테란의 핵심 비밀과 관련된 정보를 유출하지 않도록 하는 책임을 맡고 있습니다.</Text>
		</Replace>
		<Replace Tag="LOC_LEADER_OP_FIAMMETTA_QUOTE" Language="ko_KR">
			<Text>성공과 실패 사이에는 요행이 없습니다.</Text>
		</Replace>
		<Replace Tag="LOC_LEADER_OP_FEDERICO_NAME" Language="ko_KR">
			<Text>페데리코 지알로</Text>
		</Replace>
		<Replace Tag="LOC_LOADING_INFO_LEADER_OP_FEDERICO" Language="ko_KR">
			<Text>라테라노 공증인의 법률 전문 집행자인 애도자는 라테란의 1대 13의 시민권을 행사하며, 현 라테란 교황 복음 전도사 11세로부터 직접 &quot;성인&quot;이라는 칭호를 받습니다.</Text>
		</Replace>
		<Replace Tag="LOC_LEADER_OP_FEDERICO_QUOTE" Language="ko_KR">
			<Text>깨진 금기는 더 이상 그 힘을 유지하지 못합니다.</Text>
		</Replace>
		<Replace Tag="LOC_LEADER_OP_YVANGELISTA_XI_NAME" Language="ko_KR">
			<Text>에반젤리스타 11세</Text>
		</Replace>
		<Replace Tag="LOC_LOADING_INFO_LEADER_OP_YVANGELISTA_XI" Language="ko_KR">
			<Text>현 교황은 라테란의 '법'에 대한 진실을 알고 있으며, '율법'의 축복이 온 땅에 퍼질 수 없다는 것을 알면서도 여전히 국가 간 협력을 장려하고 있습니다.</Text>
		</Replace>
		<Replace Tag="LOC_LEADER_OP_YVANGELISTA_XI_QUOTE" Language="ko_KR">
			<Text>우리는 라테란뿐만 아니라 테라의 모든 국가에서 도전에 직면해 있습니다.</Text>
		</Replace>
		<Replace Tag="LOC_CITY_NAME_OP_LATERANO_1" Language="ko_KR">
			<Text>러틀랜드 시티</Text>
		</Replace>
		<Replace Tag="LOC_CITY_NAME_OP_LATERANO_2" Language="ko_KR">
			<Text>암브로시오</Text>
		</Replace>
		<Replace Tag="LOC_CITY_NAME_OP_LATERANO_3" Language="ko_KR">
			<Text>스티븐</Text>
		</Replace>
		<Replace Tag="LOC_CITY_NAME_OP_LATERANO_4" Language="ko_KR">
			<Text>페이버</Text>
		</Replace>
		<Replace Tag="LOC_CITY_NAME_OP_LATERANO_5" Language="ko_KR">
			<Text>게펜</Text>
		</Replace>
		<Replace Tag="LOC_CITY_NAME_OP_LATERANO_6" Language="ko_KR">
			<Text>마이클 레온</Text>
		</Replace>
		<Replace Tag="LOC_CITY_NAME_OP_LATERANO_7" Language="ko_KR">
			<Text>산 마르소</Text>
		</Replace>
		<Replace Tag="LOC_CITY_NAME_OP_LATERANO_8" Language="ko_KR">
			<Text>라벤나</Text>
		</Replace>
		<Replace Tag="LOC_CITY_NAME_OP_LATERANO_9" Language="ko_KR">
			<Text>볼로냐</Text>
		</Replace>
		<Replace Tag="LOC_CITY_NAME_OP_LATERANO_10" Language="ko_KR">
			<Text>페라라</Text>
		</Replace>
		<Replace Tag="LOC_CITY_NAME_OP_LATERANO_11" Language="ko_KR">
			<Text>치비타베키아</Text>
		</Replace>
		<Replace Tag="LOC_CITY_NAME_OP_LATERANO_12" Language="ko_KR">
			<Text>페루자</Text>
		</Replace>
		<Replace Tag="LOC_CITY_NAME_OP_LATERANO_13" Language="ko_KR">
			<Text>아시시</Text>
		</Replace>
		<Replace Tag="LOC_CITY_NAME_OP_LATERANO_14" Language="ko_KR">
			<Text>오르비에토</Text>
		</Replace>
		<Replace Tag="LOC_CITY_NAME_OP_LATERANO_15" Language="ko_KR">
			<Text>세니갈리아</Text>
		</Replace>
		<Replace Tag="LOC_CITY_NAME_OP_LATERANO_16" Language="ko_KR">
			<Text>안코나</Text>
		</Replace>
		<Replace Tag="LOC_CITY_NAME_OP_LATERANO_17" Language="ko_KR">
			<Text>구비오</Text>
		</Replace>
		<Replace Tag="LOC_CITY_NAME_OP_LATERANO_18" Language="ko_KR">
			<Text>카메리노</Text>
		</Replace>
		<Replace Tag="LOC_CITY_NAME_OP_LATERANO_19" Language="ko_KR">
			<Text>페르모</Text>
		</Replace>
		<Replace Tag="LOC_CITY_NAME_OP_LATERANO_20" Language="ko_KR">
			<Text>리미니</Text>
		</Replace>
		<Replace Tag="LOC_CITY_NAME_OP_LATERANO_21" Language="ko_KR">
			<Text>우르비노</Text>
		</Replace>
		<Replace Tag="LOC_CITY_NAME_OP_LATERANO_22" Language="ko_KR">
			<Text>베네벤토</Text>
		</Replace>
		<Replace Tag="LOC_CITY_NAME_OP_LATERANO_23" Language="ko_KR">
			<Text>폰테코르보</Text>
		</Replace>
		<Replace Tag="LOC_CITY_NAME_OP_LATERANO_24" Language="ko_KR">
			<Text>아스콜리</Text>
		</Replace>
		<Replace Tag="LOC_CITY_NAME_OP_LATERANO_25" Language="ko_KR">
			<Text>간돌포</Text>
		</Replace>
		<Replace Tag="LOC_CITY_NAME_OP_LATERANO_26" Language="ko_KR">
			<Text>아비뇽</Text>
		</Replace>
		<Replace Tag="LOC_CITIZEN_OP_LATERANO_MALE_NAME_1" Language="ko_KR">
			<Text>조반니</Text>
		</Replace>
		<Replace Tag="LOC_CITIZEN_OP_LATERANO_MALE_NAME_2" Language="ko_KR">
			<Text>파비오</Text>
		</Replace>
		<Replace Tag="LOC_CITIZEN_OP_LATERANO_MALE_NAME_3" Language="ko_KR">
			<Text>줄리오</Text>
		</Replace>
		<Replace Tag="LOC_CITIZEN_OP_LATERANO_MALE_NAME_4" Language="ko_KR">
			<Text>데조</Text>
		</Replace>
		<Replace Tag="LOC_CITIZEN_OP_LATERANO_MALE_NAME_5" Language="ko_KR">
			<Text>페데리코</Text>
		</Replace>
		<Replace Tag="LOC_CITIZEN_OP_LATERANO_MALE_NAME_6" Language="ko_KR">
			<Text>프란체스코</Text>
		</Replace>
		<Replace Tag="LOC_CITIZEN_OP_LATERANO_MALE_NAME_7" Language="ko_KR">
			<Text>아르데라노</Text>
		</Replace>
		<Replace Tag="LOC_CITIZEN_OP_LATERANO_MALE_NAME_8" Language="ko_KR">
			<Text>지암바티스타</Text>
		</Replace>
		<Replace Tag="LOC_CITIZEN_OP_LATERANO_MALE_NAME_9" Language="ko_KR">
			<Text>파브리치오</Text>
		</Replace>
		<Replace Tag="LOC_CITIZEN_OP_LATERANO_MALE_NAME_10" Language="ko_KR">
			<Text>스테파노 토레그로사</Text>
		</Replace>
		<Replace Tag="LOC_CITIZEN_OP_LATERANO_MODERN_MALE_NAME_1" Language="ko_KR">
			<Text>폴 조지</Text>
		</Replace>
		<Replace Tag="LOC_CITIZEN_OP_LATERANO_MODERN_MALE_NAME_2" Language="ko_KR">
			<Text>니콜로</Text>
		</Replace>
		<Replace Tag="LOC_CITIZEN_OP_LATERANO_MODERN_MALE_NAME_3" Language="ko_KR">
			<Text>안소니</Text>
		</Replace>
		<Replace Tag="LOC_CITIZEN_OP_LATERANO_MODERN_MALE_NAME_4" Language="ko_KR">
			<Text>주세페</Text>
		</Replace>
		<Replace Tag="LOC_CITIZEN_OP_LATERANO_MODERN_MALE_NAME_5" Language="ko_KR">
			<Text>실비오</Text>
		</Replace>
		<Replace Tag="LOC_CITIZEN_OP_LATERANO_MODERN_MALE_NAME_6" Language="ko_KR">
			<Text>알베리코</Text>
		</Replace>
		<Replace Tag="LOC_CITIZEN_OP_LATERANO_MODERN_MALE_NAME_7" Language="ko_KR">
			<Text>로도윅</Text>
		</Replace>
		<Replace Tag="LOC_CITIZEN_OP_LATERANO_MODERN_MALE_NAME_8" Language="ko_KR">
			<Text>이그나치오</Text>
		</Replace>
		<Replace Tag="LOC_CITIZEN_OP_LATERANO_MODERN_MALE_NAME_9" Language="ko_KR">
			<Text>라짜로</Text>
		</Replace>
		<Replace Tag="LOC_CITIZEN_OP_LATERANO_MODERN_MALE_NAME_10" Language="ko_KR">
			<Text>프랜시스</Text>
		</Replace>
		<Replace Tag="LOC_CITIZEN_OP_LATERANO_FEMALE_NAME_1" Language="ko_KR">
			<Text>줄리아</Text>
		</Replace>
		<Replace Tag="LOC_CITIZEN_OP_LATERANO_FEMALE_NAME_2" Language="ko_KR">
			<Text>클라라</Text>
		</Replace>
		<Replace Tag="LOC_CITIZEN_OP_LATERANO_FEMALE_NAME_3" Language="ko_KR">
			<Text>마르티나</Text>
		</Replace>
		<Replace Tag="LOC_CITIZEN_OP_LATERANO_FEMALE_NAME_4" Language="ko_KR">
			<Text>실비아</Text>
		</Replace>
		<Replace Tag="LOC_CITIZEN_OP_LATERANO_FEMALE_NAME_5" Language="ko_KR">
			<Text>프랜시스</Text>
		</Replace>
		<Replace Tag="LOC_CITIZEN_OP_LATERANO_FEMALE_NAME_6" Language="ko_KR">
			<Text>엘리사</Text>
		</Replace>
		<Replace Tag="LOC_CITIZEN_OP_LATERANO_FEMALE_NAME_7" Language="ko_KR">
			<Text>페데리카</Text>
		</Replace>
		<Replace Tag="LOC_CITIZEN_OP_LATERANO_FEMALE_NAME_8" Language="ko_KR">
			<Text>알레시아</Text>
		</Replace>
		<Replace Tag="LOC_CITIZEN_OP_LATERANO_FEMALE_NAME_9" Language="ko_KR">
			<Text>로라</Text>
		</Replace>
		<Replace Tag="LOC_CITIZEN_OP_LATERANO_FEMALE_NAME_10" Language="ko_KR">
			<Text>엘레나</Text>
		</Replace>
		<Replace Tag="LOC_CITIZEN_OP_LATERANO_MODERN_FEMALE_NAME_1" Language="ko_KR">
			<Text>그루지야</Text>
		</Replace>
		<Replace Tag="LOC_CITIZEN_OP_LATERANO_MODERN_FEMALE_NAME_2" Language="ko_KR">
			<Text>안나</Text>
		</Replace>
		<Replace Tag="LOC_CITIZEN_OP_LATERANO_MODERN_FEMALE_NAME_3" Language="ko_KR">
			<Text>마르타</Text>
		</Replace>
		<Replace Tag="LOC_CITIZEN_OP_LATERANO_MODERN_FEMALE_NAME_4" Language="ko_KR">
			<Text>로베르타</Text>
		</Replace>
		<Replace Tag="LOC_CITIZEN_OP_LATERANO_MODERN_FEMALE_NAME_5" Language="ko_KR">
			<Text>베아트릭스</Text>
		</Replace>
		<Replace Tag="LOC_CITIZEN_OP_LATERANO_MODERN_FEMALE_NAME_6" Language="ko_KR">
			<Text>제이다</Text>
		</Replace>
		<Replace Tag="LOC_CITIZEN_OP_LATERANO_MODERN_FEMALE_NAME_7" Language="ko_KR">
			<Text>발레리아</Text>
		</Replace>
		<Replace Tag="LOC_CITIZEN_OP_LATERANO_MODERN_FEMALE_NAME_8" Language="ko_KR">
			<Text>시몬</Text>
		</Replace>
		<Replace Tag="LOC_CITIZEN_OP_LATERANO_MODERN_FEMALE_NAME_9" Language="ko_KR">
			<Text>베네데타</Text>
		</Replace>
		<Replace Tag="LOC_CITIZEN_OP_LATERANO_MODERN_FEMALE_NAME_10" Language="ko_KR">
			<Text>루도비카</Text>
		</Replace>
		<Replace Tag="LOC_LATERANO_LAUNCH_BUTTON_TOOLTIP" Language="ko_KR">
			<Text>{LOC_TRAIT_CIVILIZATION_PIVOT_OF_HEAVEN_NAME}[NEWLINE][NEWLINE]특성 고유의 능력에 액세스합니다.</Text>
		</Replace>
		<Replace Tag="LOC_LATERANO_EXTRA_BELIEF_AVAILABLE" Language="ko_KR">
			<Text>당신은 당신의 종교에 더 많은 신앙을 통합할 수 있습니다.</Text>
		</Replace>
		<Replace Tag="LOC_LATERANO_EXTRA_BELIEF_INFO" Language="ko_KR">
			<Text>종교에 {1_Amount} 신앙을 추가할 수도 있습니다.</Text>
		</Replace>
		<Replace Tag="LOC_YVANGELISTA_PANEL_TIP" Language="ko_KR">
			<Text>{LOC_TRAIT_LEADER_LATERAN_DECLARATION_NAME}[NEWLINE][NEWLINE]귀하가 아닌 과거의 훌륭한 인재를 채용하세요.</Text>
		</Replace>
		<Replace Tag="LOC_YVANGELISTA_USED_BELONG_TO" Language="ko_KR">
			<Text>위대한 사람은 한때 속해 있었다</Text>
		</Replace>
		<Replace Tag="LOC_YVANGELISTA_FIATH_RECRUIT" Language="ko_KR">
			<Text>신앙모집</Text>
		</Replace>
		<Replace Tag="LOC_YVANGELISTA_PICK_PRESET_ALL" Language="ko_KR">
			<Text>모든 유형</Text>
		</Replace>
		<Replace Tag="LOC_YVANGELISTA_NO_RECRUITABLE" Language="ko_KR">
			<Text>훌륭한 인재를 영입할 수 없음</Text>
		</Replace>
		<Replace Tag="LOC_NO_ENOUGH_FAITH" Language="ko_KR">
			<Text>믿음의 가치가 충분하지 않습니다.</Text>
		</Replace>
		<Replace Tag="LOC_NO_MATCHED_DOMAIN_DISTRICT" Language="ko_KR">
			<Text>해당 지역 없음</Text>
		</Replace>
		<Replace Tag="LOC_YVANGELISTA_RECRUIT_REPAY_HEADER_TEXT" Language="ko_KR">
			<Text>{LOC_TRAIT_LEADER_LATERAN_선언_이름}</Text>
		</Replace>
		<Replace Tag="LOC_YVANGELISTA_RECRUIT_REPAY_HEADER_INFO" Language="ko_KR">
			<Text>한때 귀하에게 속했던 위대한 인물 {1_IndividualName}이(가) 플레이어에 의해 다시 모집되었으며 귀하는 {2_Amount} [ICON_FAITH] 신앙 포인트를 보상으로 받았습니다.</Text>
		</Replace>
		<Replace Tag="LOC_RELIGION_OPH_LATERAN" Language="ko_KR">
			<Text>라테라니즘</Text>
		</Replace>
		<Replace Tag="LOC_TRAIT_CIVILIZATION_PIVOT_OF_HEAVEN_NAME" Language="ko_KR">
			<Text>파라다이스 펄크럼</Text>
		</Replace>
		<Replace Tag="LOC_TRAIT_CIVILIZATION_PIVOT_OF_HEAVEN_DESCRIPTION" Language="ko_KR">
			<Text>오직 성전만이 일어날 수 있다. [NEWLINE]자본 이득은 +3 [ICON_GREATPROPHET] 위대한 선지자 포인트와 +3 [ICON_FAITH] 신앙입니다. [NEWLINE]종교를 만든 후에는 모든 신앙을 완성할 수 있습니다. 그리고 각 계시의 돌탑마다 1개의 신앙을 추가할 수 있습니다(최대 6개의 추가 신앙).</Text>
		</Replace>
		<Replace Tag="LOC_TRAIT_LEADER_REQUIEM_MASS_NAME" Language="ko_KR">
			<Text>레퀴엠 미사</Text>
		</Replace>
		<Replace Tag="LOC_TRAIT_LEADER_REQUIEM_MASS_DESCRIPTION" Language="ko_KR">
			<Text>[ICON_GREATPERSON]이 활성화되면 10타일 이내의 도시에 종교 압력 600점을 적용합니다. [NEWLINE] 자신의 종교를 믿는 자신의 도시에 있는 성지(위대한 예술가), 아카데미(위대한 과학자), 극장 광장(위대한 음악가) 건물은 추가로 [ICON_GREATPERSON]명의 위인 포인트를 생성하고 해당 생산품을 +1 제공합니다. 같은 이름의 건물에 대해.</Text>
		</Replace>
		<Replace Tag="LOC_TRAIT_LEADER_EVERLASTING_JOURNEY_NAME" Language="ko_KR">
			<Text>끝나지 않은 여정</Text>
		</Replace>
		<Replace Tag="LOC_TRAIT_LEADER_EVERLASTING_JOURNEY_DESCRIPTION" Language="ko_KR">
			<Text>정찰병과 원거리 유닛의 이동력이 +1 [ICON_MOVEMENT] 증가합니다. 인프라를 구축하고 해당 기술이나 지방자치단체를 잠금 해제하면 해당 프로젝트를 잠금해제하여 다음과 같은 능력을 발휘할 수 있습니다. [NEWLINE] 경건한 기금 모금: 성지 지역 + 외국 무역 지방자치단체. [NEWLINE]미래의 씨앗: 농장 개선 + 관개 기술. [NEWLINE] Landon Tactics: 군사 캠프 지역 + 전술 기술. [NEWLINE] 과거가 생생하게 살아납니다: 극장 광장 지역 + 자연사 자치단체.</Text>
		</Replace>
		<Replace Tag="LOC_TRAIT_LEADER_APOCALYPSE_PUNISHER_NAME" Language="ko_KR">
			<Text>종말의 처벌</Text>
		</Replace>
		<Replace Tag="LOC_TRAIT_LEADER_APOCALYPSE_PUNISHER_DESCRIPTION" Language="ko_KR">
			<Text>각 계시의 탑은 총독 타이틀에 +1 [ICON_GOVERNOR]를 제공합니다. [NEWLINE]당신의 종교를 따르는 도시에 [ICON_ENVOY]명의 사절을 두 배 더 많이 보내세요. 관할권에 속한 각 도시 국가는 해당 유형에 따라 지역 건물에 해당하는 생산량을 +20% 제공합니다(각 도시 국가 유형은 최대 3개까지 중첩 가능). [NEWLINE]고유 총독 '타락한 천사' 모스테마가 있습니다.</Text>
		</Replace>
		<Replace Tag="LOC_TRAIT_LEADER_DAMNATUS_EX_FOEDERE_NAME" Language="ko_KR">
			<Text>언약의 심판</Text>
		</Replace>
		<Replace Tag="LOC_TRAIT_LEADER_DAMNATUS_EX_FOEDERE_DESCRIPTION" Language="ko_KR">
			<Text>정식 전쟁을 시작할 수 있으며, 주류 문명과의 전쟁 시 이동성이 +1 [ICON_MOVEMENT], 전투력이 +5 [ICON_STRENGTH]됩니다. [NEWLINE] 각 인구는 추가로 +0.5 충성 압력을 방출하고 +0.5 [ICON_CULTURE] 문화와 [ICON_FAITH] 신앙을 생산합니다. 도시가 라테란에 의해 설립되지 않은 경우 이러한 보너스는 두 배가 됩니다. [NEWLINE]전투에서 승리하면 자동으로 주변 도시에 종교가 전파됩니다.</Text>
		</Replace>
		<Replace Tag="LOC_TRAIT_LEADER_LATERAN_DECLARATION_NAME" Language="ko_KR">
			<Text>라테라노의 주장</Text>
		</Replace>
		<Replace Tag="LOC_TRAIT_LEADER_LATERAN_DECLARATION_DESCRIPTION" Language="ko_KR">
			<Text>주류 문명과 전쟁 중이 아닐 때 신앙 가치 +30% [ICON_FAITH], 위인 점수 +15%, 종교 압력 및 확산 범위 +100%. [NEWLINE]소액의 [ICON_FAITH] 신앙 비용으로 다른 문명의 일부였던 과거의 위인 [ICON_GREATPERSON]명을 모집할 수 있습니다. [NEWLINE]당신이 모집하는 각 [ICON_GREATPERSON]에 대해 당신의 지역은 그에 상응하는 생산량을 +2 얻습니다.</Text>
		</Replace>
		<Replace Tag="LOC_BUILDING_REVELATION_TOWER_NAME" Language="ko_KR">
			<Text>계시의 탑</Text>
		</Replace>
		<Replace Tag="LOC_BUILDING_REVELATION_TOWER_DESCRIPTION" Language="ko_KR">
			<Text>기념물을 대체하는 라테란 특유의 건물. 도시의 주요 종교의 각 신조에 대해 +1 [ICON_CULTURE] 문화와 +1 [ICON_FAITH] 신앙을 얻습니다. 매 라운드마다 도시의 충성도가 8씩 증가합니다.</Text>
		</Replace>
		<Replace Tag="LOC_DISTRICT_LATERAN_BASILICA_NAME" Language="ko_KR">
			<Text>라테란 대성당</Text>
		</Replace>
		<Replace Tag="LOC_DISTRICT_LATERAN_BASILICA_DESCRIPTION" Language="ko_KR">
			<Text>성지를 대체하고 건설 비용이 더 저렴한 라테란 특수 지역입니다. +4 [ICON_FAITH] 신앙 인접 보너스로 시작합니다. [NEWLINE] 이 지역과 그 안에 있는 각 건물의 기초는 도시에 1개의 보너스 자원을 추가합니다. [ICON_FAITH] 신앙 가치 및 [ICON_FOOD] 전략적 자원 +1 [ICON_SCIENCE] 기술 가치 및 [ICON_PRODUCTION] 사치 자원 + 1 [ICON_CULTURE] 문화 가치와 [ICON_GOLD] 금화입니다.</Text>
		</Replace>
		<Replace Tag="LOC_UNIT_LATERAN_PONTIFICA_COHORS_NAME" Language="ko_KR">
			<Text>라테라노 경비대</Text>
		</Replace>
		<Replace Tag="LOC_UNIT_LATERAN_PONTIFICA_COHORS_DESCRIPTION" Language="ko_KR">
			<Text>독특한 진급을 제공하는 러틀랜드의 독특한 유닛입니다. 훈련할 수 없으며, 신전을 지을 때만 얻을 수 있습니다. [NEWLINE] 플레이어의 기술과 도시 수준이 높아질 때마다 승급이 잠금 해제되고 전투력이 높아집니다.</Text>
		</Replace>
		<Replace Tag="LOC_PROMOTION_CLASS_LATERAN_PONTIFICA_COHORS_NAME" Language="ko_KR">
			<Text>라테란 수비대</Text>
		</Replace>
		<Replace Tag="LOC_PROMOTION_LATERAN_PONTIFICA_COHORS_1_NAME" Language="ko_KR">
			<Text>계발</Text>
		</Replace>
		<Replace Tag="LOC_PROMOTION_LATERAN_PONTIFICA_COHORS_1_DESC" Language="ko_KR">
			<Text>전투 승리 시 대상 전투력의 100%에 해당하는 [ICON_FAITH] 신앙치를 획득합니다.</Text>
		</Replace>
		<Replace Tag="LOC_PROMOTION_LATERAN_PONTIFICA_COHORS_2_NAME" Language="ko_KR">
			<Text>晋铎</Text>
		</Replace>
		<Replace Tag="LOC_PROMOTION_LATERAN_PONTIFICA_COHORS_2_DESC" Language="ko_KR">
			<Text>통제 구역을 무시하고 주요 문명 유닛을 죽이면 자동으로 주변 도시로 종교가 전파됩니다.</Text>
		</Replace>
		<Replace Tag="LOC_PROMOTION_LATERAN_PONTIFICA_COHORS_3_NAME" Language="ko_KR">
			<Text>계발</Text>
		</Replace>
		<Replace Tag="LOC_PROMOTION_LATERAN_PONTIFICA_COHORS_3_DESC" Language="ko_KR">
			<Text>이동력 +1 [ICON_MOVEMENT], 지형 무시, 강 건너기 시 [ICON_MOVEMENT] 이동 피해.</Text>
		</Replace>
		<Replace Tag="LOC_PROMOTION_LATERAN_PONTIFICA_COHORS_4_NAME" Language="ko_KR">
			<Text>성임</Text>
		</Replace>
		<Replace Tag="LOC_PROMOTION_LATERAN_PONTIFICA_COHORS_4_DESC" Language="ko_KR">
			<Text>다른 종교의 문명과 싸울 때 전투력이 10 [ICON_STRENGTH] 증가합니다.</Text>
		</Replace>
		<Replace Tag="LOC_PROMOTION_LATERAN_PONTIFICA_COHORS_5_NAME" Language="ko_KR">
			<Text>규율</Text>
		</Replace>
		<Replace Tag="LOC_PROMOTION_LATERAN_PONTIFICA_COHORS_5_DESC" Language="ko_KR">
			<Text>지역 방어에 대한 피해 감소는 없습니다.</Text>
		</Replace>
		<Replace Tag="LOC_PROMOTION_LATERAN_PONTIFICA_COHORS_6_NAME" Language="ko_KR">
			<Text>홍보하다</Text>
		</Replace>
		<Replace Tag="LOC_PROMOTION_LATERAN_PONTIFICA_COHORS_6_DESC" Language="ko_KR">
			<Text>라운드당 1번의 추가 공격이 가능합니다.</Text>
		</Replace>
		<Replace Tag="LOC_ARCHETTO_1_FAITH" Language="ko_KR">
			<Text>+{1_Amount} [ICON_FAITH] 신앙(내일의 씨앗).</Text>
		</Replace>
		<Replace Tag="LOC_LATERAN_BASILICA_SELF_FAITH" Language="ko_KR">
			<Text>+{1_Amount} [ICON_FAITH] 신앙 가치는 지역 자체에서 나옵니다.</Text>
		</Replace>
		<Replace Tag="LOC_PROJECT_ARCHETTO_PROJECT_HOLY_SITE_NAME" Language="ko_KR">
			<Text>종교적으로 돈을 모으다</Text>
		</Replace>
		<Replace Tag="LOC_PROJECT_ARCHETTO_PROJECT_HOLY_SITE_DESCRIPTION" Language="ko_KR">
			<Text>3 [ICON_TRADEROUTE] 교역로 용량을 얻고 성지는 [ICON_FAITH] 신앙 인접 보너스와 동일한 [ICON_GOLD] 금을 제공합니다.</Text>
		</Replace>
		<Replace Tag="LOC_PROJECT_ARCHETTO_PROJECT_FARM_NAME" Language="ko_KR">
			<Text>내일의 씨앗</Text>
		</Replace>
		<Replace Tag="LOC_PROJECT_ARCHETTO_PROJECT_FARM_DESCRIPTION" Language="ko_KR">
			<Text>농장 및 농장은 [ICON_FOOD] 식량을 +1하고 성지에 표준 인접 보너스를 제공합니다.</Text>
		</Replace>
		<Replace Tag="LOC_PROJECT_ARCHETTO_PROJECT_ENCAMPMENT_NAME" Language="ko_KR">
			<Text>랜던 전술</Text>
		</Replace>
		<Replace Tag="LOC_PROJECT_ARCHETTO_PROJECT_ENCAMPMENT_DESCRIPTION" Language="ko_KR">
			<Text>원거리 유닛과 수비대는 +1 [ICON_RANGED] 공격 범위를 가지며 공격 후 이동할 수 있습니다.</Text>
		</Replace>
		<Replace Tag="LOC_PROJECT_ARCHETTO_PROJECT_THEATER_NAME" Language="ko_KR">
			<Text>옛날이 다시 온다</Text>
		</Replace>
		<Replace Tag="LOC_PROJECT_ARCHETTO_PROJECT_THEATER_DESCRIPTION" Language="ko_KR">
			<Text>모든 지역은 +4 [ICON_CULTURE] 문화적 가치를 얻고, 극장 광장이나 성지와 인접하면 관광 공연도 +3 [ICON_TOURISM] 받습니다.</Text>
		</Replace>
		<Replace Tag="LOC_ABILITY_ARCHETTO_PROJECT_ENCAMPMENT_NAME" Language="ko_KR">
			<Text>{LOC_PROJECT_ARCHETTO_PROJECT_ENCAMPMENT_NAME}</Text>
		</Replace>
		<Replace Tag="LOC_ABILITY_ARCHETTO_PROJECT_ENCAMPMENT_DESCRIPTION" Language="ko_KR">
			<Text>+1 [ICON_RANGED] 공격 범위, 공격 후 이동이 가능해집니다. ({LOC_ABILITY_ARCHETTO_PROJECT_ENCAMPMENT_NAME})</Text>
		</Replace>
		<Replace Tag="LOC_MODFEAT_FEDERICO_WARTIME_BONUS_STRENGTH" Language="ko_KR">
			<Text>+{1_Amount}는 주류 문명({LOC_TRAIT_LEADER_DAMNATUS_EX_FOEDERE_NAME})과 전쟁 중입니다.</Text>
		</Replace>
		<Replace Tag="LOC_MODFEAT_PONTIFICA_COHORS_STRENGTH_BONUS_STRENGTH_EFFECT" Language="ko_KR">
			<Text>Rutland Garrison 숙소의 +{Property}</Text>
		</Replace>
		<Replace Tag="LOC_MODFEAT_PONTIFICA_COHORS_PROMOTION_4_COMBAT_STRENGTH" Language="ko_KR">
			<Text>이교도 유닛({LOC_PROMOTION_LATERAN_PONTIFICA_COHORS_4_NAME})에 대해 +{1_Amount}</Text>
		</Replace>
		<Replace Tag="LOC_VIZSOURCE_MOSTIMA" Language="ko_KR">
			<Text>자물쇠와 열쇠</Text>
		</Replace>
		<Replace Tag="LOC_VIZSOURCE_ACTION_MOSTIMA" Language="ko_KR">
			<Text>모스티마 주지사 최종 승진</Text>
		</Replace>
		<Replace Tag="LOC_GOSSIP_SOURCE_MOSTIMA" Language="ko_KR">
			<Text>귀하의 배송업체({1_Name})가 Mostema로부터 정보를 받았습니다.</Text>
		</Replace>
		<Replace Tag="LOC_GOVERNOR_OPH_MOSTIMA_NAME" Language="ko_KR">
			<Text>모스티마</Text>
		</Replace>
		<Replace Tag="LOC_GOVERNOR_OPH_MOSTIMA_TITLE" Language="ko_KR">
			<Text>타천사</Text>
		</Replace>
		<Replace Tag="LOC_GOVERNOR_OPH_MOSTIMA_SHORT_TITLE" Language="ko_KR">
			<Text>타천사</Text>
		</Replace>
		<Replace Tag="LOC_GOVERNOR_OPH_MOSTIMA_DESCRIPTION" Language="ko_KR">
			<Text>모스테마의 적들은 시간이 느려진 것처럼 끈적끈적한 느낌을 받습니다. 하지만 우리는 시간을 방해할 수 있는 오리지늄 기술에 대해 들어본 적도 없고, 발견한 적도 없습니다. 그녀의 정체만큼이나 신비로움이 가득합니다. [NEWLINE]하지만 마법사로서 그녀의 가치는 그 이상입니다. 그녀에게 최고의 무대를 선사하고 준비할 시간을 조금만 더 주면 그녀가 다른 지팡이를 꺼내면 아무리 공격이 강력해도 사라집니다.</Text>
		</Replace>
		<Replace Tag="LOC_GOVERNOR_PROMOTION_OPH_MOSTIMA_BASE_NAME" Language="ko_KR">
			<Text>전령</Text>
		</Replace>
		<Replace Tag="LOC_GOVERNOR_PROMOTION_OPH_MOSTIMA_BASE_DESCRIPTION" Language="ko_KR">
			<Text>다른 문명의 도시로 보낼 수 있습니다. 도시 국가로 보낼 경우 효과는 [ICON_ENVOY] 사절 2명과 같습니다.</Text>
		</Replace>
		<Replace Tag="LOC_GOVERNOR_PROMOTION_OPH_MOSTIMA_L1_NAME" Language="ko_KR">
			<Text>맞춤형 케이프</Text>
		</Replace>
		<Replace Tag="LOC_GOVERNOR_PROMOTION_OPH_MOSTIMA_L1_DESCRIPTION" Language="ko_KR">
			<Text>도시 국가에 고용되면 해당 도시 국가에 파견되는 사절의 수가 두 배가 됩니다.</Text>
		</Replace>
		<Replace Tag="LOC_GOVERNOR_PROMOTION_OPH_MOSTIMA_L2_NAME" Language="ko_KR">
			<Text>물류위탁</Text>
		</Replace>
		<Replace Tag="LOC_GOVERNOR_PROMOTION_OPH_MOSTIMA_L2_DESCRIPTION" Language="ko_KR">
			<Text>도시 국가에서 활동하면 도시 국가의 사치 자원과 전략 자원을 획득하게 됩니다. 도시 국가 유닛 모집 비용이 30% 감소합니다.</Text>
		</Replace>
		<Replace Tag="LOC_GOVERNOR_PROMOTION_OPH_MOSTIMA_R1_NAME" Language="ko_KR">
			<Text>주관적인 속도 저하</Text>
		</Replace>
		<Replace Tag="LOC_GOVERNOR_PROMOTION_OPH_MOSTIMA_R1_DESCRIPTION" Language="ko_KR">
			<Text>다른 주류 문명의 도시에서 일할 때 도시의 생산량은 -30%입니다.</Text>
		</Replace>
		<Replace Tag="LOC_GOVERNOR_PROMOTION_OPH_MOSTIMA_R2_NAME" Language="ko_KR">
			<Text>타이밍의 핵심</Text>
		</Replace>
		<Replace Tag="LOC_GOVERNOR_PROMOTION_OPH_MOSTIMA_R2_DESCRIPTION" Language="ko_KR">
			<Text>{LOC_GOVERNOR_PROMOTION_OPH_MOSTIMA_R1_NAME}의 효과가 두 배로 증가합니다. 다른 주류 문명의 도시에서 활동할 때 6칸 내의 비우호적 유닛의 이동력은 -1입니다.</Text>
		</Replace>
		<Replace Tag="LOC_GOVERNOR_PROMOTION_OPH_MOSTIMA_FINAL_NAME" Language="ko_KR">
			<Text>자물쇠와 열쇠</Text>
		</Replace>
		<Replace Tag="LOC_GOVERNOR_PROMOTION_OPH_MOSTIMA_FINAL_DESCRIPTION" Language="ko_KR">
			<Text>전체 지도가 공개됩니다. 모든 문명에 대한 외교 가시성이 +1됩니다.</Text>
		</Replace>
		<Replace Tag="LOC_AGENDA_LEADER_OP_VIRTUOSA_LTRN_NAME" Language="ko_KR">
			<Text>황금 엑스터시</Text>
		</Replace>
		<Replace Tag="LOC_AGENDA_LEADER_OP_VIRTUOSA_LTRN_DESCRIPTION" Language="ko_KR">
			<Text>종교와 문화를 적극적으로 발전시키는 데 전념하고, 같은 일을 하는 문명을 좋아합니다.</Text>
		</Replace>
		<Replace Tag="LOC_AGENDA_LEADER_OP_FEDERICO_NAME" Language="ko_KR">
			<Text>선택된 사람</Text>
		</Replace>
		<Replace Tag="LOC_AGENDA_LEADER_OP_FEDERICO_DESCRIPTION" Language="ko_KR">
			<Text>그들은 자신들의 종교를 받아들이고 이교도들에게 적대적인 문명처럼 자신들의 종교를 장려하기 위해 노력합니다.</Text>
		</Replace>
		<Replace Tag="LOC_AGENDA_LEADER_OP_ARCHETTO_NAME" Language="ko_KR">
			<Text>벽돌과 모르타르 추가하기</Text>
		</Replace>
		<Replace Tag="LOC_AGENDA_LEADER_OP_ARCHETTO_DESCRIPTION" Language="ko_KR">
			<Text>각 도시의 기반 시설을 개발하는 데 중점을 두고 다른 문명과의 무역을 기꺼이 할 것입니다.</Text>
		</Replace>
		<Replace Tag="LOC_AGENDA_LEADER_OP_FIAMMETTA_NAME" Language="ko_KR">
			<Text>내가 앞장서서</Text>
		</Replace>
		<Replace Tag="LOC_AGENDA_LEADER_OP_FIAMMETTA_DESCRIPTION" Language="ko_KR">
			<Text>Lezhong은 영향력을 확대하기 위해 모든 문명과 광범위한 교류에 전념하고 있습니다. 도시 국가를 놓고 경쟁하는 문명을 싫어합니다.</Text>
		</Replace>
		<Replace Tag="LOC_AGENDA_LEADER_OP_YVANGELISTA_XI_NAME" Language="ko_KR">
			<Text>국가 정상회담</Text>
		</Replace>
		<Replace Tag="LOC_AGENDA_LEADER_OP_YVANGELISTA_XI_DESCRIPTION" Language="ko_KR">
			<Text>세계 평화와 공동 발전을 위해 헌신하고, 인재를 모집하며, 이를 실천하는 문명을 좋아하세요.</Text>
		</Replace>
	</LocalizedText>
</GameData>
