<?xml version="1.0" encoding="utf-8"?>
<!-- Automatically translated with the help of google translate.-->
<!-- Mon Jul 15 12:35:27 2024-->
<GameData>
	<LocalizedText>
		<Replace Tag="LOC_LEADER_BA_OMAGARI_HARE_NAME" Language="de_DE">
			<Text>Omagari-Hase</Text>
		</Replace>
		<Replace Tag="LOC_TRAIT_EMP_DRONE_NAME" Language="de_DE">
			<Text>EMP-Drohneneinsatz</Text>
		</Replace>
		<Replace Tag="LOC_TRAIT_EMP_DRONE_DESCRIPTION" Language="de_DE">
			<Text>Das Erforschen von Elektrizität erhöht den Erfahrungsgewinn aller Scout-Einheiten um +100 %, und das Erforschen von Computer führt dazu, dass alle Scout-Einheiten 10.000 [ICON_Movement] Bewegung zum Plündern aufwenden.</Text>
		</Replace>
		<Replace Tag="LOC_LEADER_BA_OMAGARI_HARE_QUOTE" Language="de_DE">
			<Text>Sollen wir es nun ohne zu zögern umrühren?</Text>
		</Replace>
		<Replace Tag="LOC_ABILITY_HARE_EXP_BONUS_DESCRIPTION" Language="de_DE">
			<Text>Erleben Sie +100 % in allen Situationen</Text>
		</Replace>
	</LocalizedText>
</GameData>
